spinekivy/__init__.py
spinekivy/atlasattachmentloader.py
spinekivy/skeletonrenderer.py
spinekivy/sprite.py
spinekivy/textureloader.py
spinekivy-0.1.1.dist-info/DESCRIPTION.rst
spinekivy-0.1.1.dist-info/METADATA
spinekivy-0.1.1.dist-info/RECORD
spinekivy-0.1.1.dist-info/WHEEL
spinekivy-0.1.1.dist-info/metadata.json
spinekivy-0.1.1.dist-info/top_level.txt
