Metadata-Version: 2.0
Name: spinekivy
Version: 0.1.1
Summary: Spine skeleton renderer for Kivy framework.
Home-page: UNKNOWN
Author: Tileworks Games and other contributors
Author-email: tileworksgames@gmail.com
License: MIT
Keywords: spine kivy
Platform: UNKNOWN
Classifier: Intended Audience :: Developers
Classifier: Intended Audience :: End Users/Desktop
Classifier: Intended Audience :: Information Technology
Classifier: Programming Language :: Python :: 2.7
Classifier: License :: OSI Approved :: MIT License
Classifier: Operating System :: Microsoft :: Windows
Classifier: Topic :: Games/Entertainment
Classifier: Topic :: Multimedia :: Graphics
Requires-Dist: kivy (>=1.8.0)
Requires-Dist: spine-cython (>=0.5.0)
